Workbook

Sheet Datos del caso
A1: Datos del caso y razones básicas (millones de USD)
A3: Concepto | B3: HealthySnacks LATAM | C3: NutriFun | D3: Combinado
A4: Ventas anuales | B4: 120 | C4: 45 | D4: =B4+C4 -> 165
A5: EBITDA | B5: 25 | C5: 8 | D5: =B5+C5 -> 33
A6: Deuda | B6: 40 | C6: 10 | D6: =B6+C6 -> 50
A7: Participación de mercado (país principal) | B7: 0.28 | C7: 0.35
A8: Margen EBITDA | B8: =B5/B4 -> 0.20833333 | C8: =C5/C4 -> 0.17777778 | D8: =D5/D4 -> 0.2
A9: Deuda / EBITDA | B9: =B6/B5 -> 1.6 | C9: =C6/C5 -> 1.25 | D9: =D6/D5 -> 1.5151515
A10: Peso de NutriFun en las ventas combinadas | C10: =C4/D4 -> 0.27272727
A12: Fuente: caso HealthySnacks–NutriFun (Universidad Tecmilenio). Cifras hipotéticas del caso en azul; en negro, fórmulas.

Sheet Costo de capital
A1: Costo de capital de NutriFun (Colombia): CAPM y WACC
A3: Componente | B3: Valor | C3: Comentario
A4: Tasa libre de riesgo (bono del Tesoro de EE. UU. a 10 años) | B4: 0.043 | C4: Supuesto en dólares
A5: Prima de riesgo país Colombia | B5: 0.028 | C5: Supuesto
A6: Beta del sector alimentos | B6: 1 | C6: Supuesto: consumo básico
A7: Prima de riesgo de mercado | B7: 0.055 | C7: Supuesto
A8: Costo del capital propio (Ke) = rf + riesgo país + beta × prima | B8: =B4+B5+B6*B7 -> 0.126 | C8: Modelo CAPM
A9: Costo de la deuda antes de impuestos (Kd) | B9: 0.11 | C9: Supuesto: deuda bancaria de corto plazo
A10: Tasa de impuesto sobre la renta en Colombia | B10: 0.35 | C10: Tasa corporativa general
A11: Costo de la deuda después de impuestos | B11: =B9*(1-B10) -> 0.0715 | C11: Kd × (1 − impuesto)
A12: Peso de la deuda (D / V) | B12: 0.2 | C12: Deuda de USD 10 M sobre un valor cercano a USD 50 M
A13: Peso del capital (E / V) | B13: =1-B12 -> 0.8
A14: Costo de capital promedio ponderado (WACC) | B14: =B13*B8+B12*B11 -> 0.1151 | C14: Tasa de descuento
A16: Cifras en azul = supuestos; en negro = fórmulas.

Sheet DCF NutriFun
A1: Valoración de NutriFun por flujo de caja libre (sin sinergias, millones de USD)
A3: Supuesto | B3: Valor | C3: Comentario
A4: Ventas 2025 | B4: ='Datos del caso'!C4 -> 45 | C4: Dato del caso
A5: Margen EBITDA | B5: ='Datos del caso'!C8 -> 0.17777778 | C5: Dato del caso (8 / 45)
A6: Capital de trabajo neto / ventas | B6: 0.15 | C6: Supuesto
A7: Tasa de impuesto | B7: ='Costo de capital'!B10 -> 0.35
A8: WACC | B8: ='Costo de capital'!B14 -> 0.1151 | C8: Hoja Costo de capital
A9: Crecimiento a perpetuidad | B9: 0.035 | C9: Supuesto
A11: Concepto | B11: 2025 (base) | C11: 2026 | D11: 2027 | E11: 2028 | F11: 2029 | G11: 2030
A12: Crecimiento de ventas | C12: 0.1 | D12: 0.1 | E12: 0.09 | F12: 0.08 | G12: 0.07
A13: Ventas | B13: =B4 -> 45 | C13: =B13*(1+C12) -> 49.5 | D13: =C13*(1+D12) -> 54.45 | E13: =D13*(1+E12) -> 59.3505 | F13: =E13*(1+F12) -> 64.09854 | G13: =F13*(1+G12) -> 68.585438
A14: EBITDA | C14: =C13*$B$5 -> 8.8 | D14: =D13*$B$5 -> 9.68 | E14: =E13*$B$5 -> 10.5512 | F14: =F13*$B$5 -> 11.395296 | G14: =G13*$B$5 -> 12.192967
A15: (−) Depreciación y amortización | C15: 1.2 | D15: 1.3 | E15: 1.4 | F15: 1.5 | G15: 1.6
A16: (=) EBIT | C16: =C14-C15 -> 7.6 | D16: =D14-D15 -> 8.38 | E16: =E14-E15 -> 9.1512 | F16: =F14-F15 -> 9.895296 | G16: =G14-G15 -> 10.592967
A17: (−) Impuesto | C17: =MAX(0,C16)*$B$7 -> 2.66 | D17: =MAX(0,D16)*$B$7 -> 2.933 | E17: =MAX(0,E16)*$B$7 -> 3.20292 | F17: =MAX(0,F16)*$B$7 -> 3.4633536 | G17: =MAX(0,G16)*$B$7 -> 3.7075384
A18: (=) NOPAT | C18: =C16-C17 -> 4.94 | D18: =D16-D17 -> 5.447 | E18: =E16-E17 -> 5.94828 | F18: =F16-F17 -> 6.4319424 | G18: =G16-G17 -> 6.8854284
A19: (+) Depreciación y amortización | C19: =C15 -> 1.2 | D19: =D15 -> 1.3 | E19: =E15 -> 1.4 | F19: =F15 -> 1.5 | G19: =G15 -> 1.6
A20: (−) Inversión en activos (CapEx) | C20: 3.5 | D20: 3.5 | E20: 2 | F20: 2 | G20: 2.1
A21: Capital de trabajo neto (saldo) | B21: =B13*$B$6 -> 6.75 | C21: =C13*$B$6 -> 7.425 | D21: =D13*$B$6 -> 8.1675 | E21: =E13*$B$6 -> 8.902575 | F21: =F13*$B$6 -> 9.614781 | G21: =G13*$B$6 -> 10.287816
A22: (−) Incremento en capital de trabajo | C22: =C21-B21 -> 0.675 | D22: =D21-C21 -> 0.7425 | E22: =E21-D21 -> 0.735075 | F22: =F21-E21 -> 0.712206 | G22: =G21-F21 -> 0.67303467
A23: (=) Flujo de caja libre | C23: =C18+C19-C20-C22 -> 1.965 | D23: =D18+D19-D20-D22 -> 2.5045 | E23: =E18+E19-E20-E22 -> 4.613205 | F23: =F18+F19-F20-F22 -> 5.2197364 | G23: =G18+G19-G20-G22 -> 5.7123937
A25: Valor terminal 2030 = FCL 2031 / (WACC − g) | G25: =G23*(1+B9)/(B8-B9) -> 73.811829
A26: Factor de descuento | C26: =1/(1+$B$8)^1 -> 0.89678056 | D26: =1/(1+$B$8)^2 -> 0.80421537 | E26: =1/(1+$B$8)^3 -> 0.72120471 | F26: =1/(1+$B$8)^4 -> 0.64676236 | G26: =1/(1+$B$8)^5 -> 0.58000391
A27: Valor presente | C27: =(C23)*C26 -> 1.7621738 | D27: =(D23)*D26 -> 2.0141574 | E27: =(E23)*E26 -> 3.3270652 | F27: =(F23)*F26 -> 3.375929 | G27: =(G23+G25)*G26 -> 46.12436
A29: Valor de la empresa (VE) sin sinergias | B29: =SUM(C27:G27) -> 56.603685
A30: EV / EBITDA 2025 | B30: =B29/'Datos del caso'!C5 -> 7.0754607
A32: Cifras en azul = supuestos; en negro = fórmulas. Paréntesis = cifras negativas.

Sheet Precio en 3 momentos
A1: Ajustes al precio de la transacción (valor de la empresa libre de deuda, millones de USD)
A3: Momento | B3: Concepto | C3: Ajuste | D3: Precio | E3: Mecanismo
A4: Supuesto: múltiplo VE / EBITDA de comparables | D4: 7.5 | E4: Golosinas y snacks saludables
A5: 1. Antes de la auditoría | B5: Valor preliminar por múltiplos (EBITDA 8 × 7.5) | D5: ='Datos del caso'!C5*D4 -> 60 | E5: Múltiplos; dato del caso: USD 60 M
A6: 2. Después de la due diligence | B6: Valor de la empresa por flujo de caja libre | C6: =D6-D5 -> -3.3963147 | D6: ='DCF NutriFun'!B29 -> 56.603685 | E6: DCF con WACC por CAPM
B7: (−) Contingencia laboral | C7: -1.8 | E7: Supuesto: pasivos laborales no registrados
B8: (−) Contingencia tributaria | C8: -2.8 | E8: Supuesto: impuestos de ejercicios anteriores
B9: Precio ajustado | D9: =D6+C7+C8 -> 52.003685 | E9: Dato del caso: USD 52 M
A10: 3. Al cierre | B10: (−) Conciliación de inventarios | C10: -1.2 | E10: Inventario físico menor al registrado
B11: (−) Capital de trabajo menor al objetivo | C11: -0.8 | E11: Ajuste contractual en la fecha de cierre
B12: Precio final (valor de la empresa) | D12: =D9+C10+C11 -> 50.003685 | E12: Dato del caso: USD 50 M
B13: (−) Pago de la deuda bancaria de NutriFun | C13: =-'Datos del caso'!C6 -> -10 | E13: Se liquida con el precio (motivación del vendedor)
B14: Monto neto para los accionistas de NutriFun | D14: =D12+C13 -> 40.003685 | E14: Valor del capital
A17: Reducción total frente al valor preliminar | D17: =D12-D5 -> -9.9963147 | E17: =D17/D5 -> -0.16660525
A18: Múltiplo final EV / EBITDA | D18: =D12/'Datos del caso'!C5 -> 6.2504607
A20: Las contingencias y ajustes en azul son supuestos que reparten los montos del caso (60 → 52 → 50).

Sheet Sinergias y VPN
A1: Sinergias, valor presente neto y recuperación de la inversión (millones de USD)
A3: Supuesto | B3: Valor | C3: Comentario
A4: Costo de producción de NutriFun / ventas | B4: 0.55 | C4: Supuesto
A5: Reducción de costos de producción por compras centralizadas | B5: 0.1 | C5: Objetivo del caso
A6: Margen EBITDA de las ventas cruzadas | B6: 0.18 | C6: Cercano al margen de ambas empresas
A7: Precio pagado (valor de la empresa) | B7: ='Precio en 3 momentos'!D12 -> 50.003685 | C7: Hoja Precio en 3 momentos
A9: Concepto | B9: 2026 | C9: 2027 | D9: 2028 | E9: 2029 | F9: 2030
A10: Grado de captura del ahorro | B10: 0.5 | C10: 1 | D10: 1 | E10: 1 | F10: 1
A11: Ventas de NutriFun (DCF) | B11: ='DCF NutriFun'!C13 -> 49.5 | C11: ='DCF NutriFun'!D13 -> 54.45 | D11: ='DCF NutriFun'!E13 -> 59.3505 | E11: ='DCF NutriFun'!F13 -> 64.09854 | F11: ='DCF NutriFun'!G13 -> 68.585438
A12: Ahorro en costos de producción | B12: =B11*$B$4*$B$5*B10 -> 1.36125 | C12: =C11*$B$4*$B$5*C10 -> 2.99475 | D12: =D11*$B$4*$B$5*D10 -> 3.2642775 | E12: =E11*$B$4*$B$5*E10 -> 3.5254197 | F12: =F11*$B$4*$B$5*F10 -> 3.7721991
A13: Ventas cruzadas (productos de una empresa en canales de la otra) | B13: 5 | C13: 10 | D13: 15 | E13: 16 | F13: 17
A14: EBITDA de las ventas cruzadas | B14: =B13*$B$6 -> 0.9 | C14: =C13*$B$6 -> 1.8 | D14: =D13*$B$6 -> 2.7 | E14: =E13*$B$6 -> 2.88 | F14: =F13*$B$6 -> 3.06
A15: (−) Costos de integración | B15: 2 | C15: 1 | D15: 0 | E15: 0 | F15: 0
A16: (=) Sinergias antes de impuestos | B16: =B12+B14-B15 -> 0.26125 | C16: =C12+C14-C15 -> 3.79475 | D16: =D12+D14-D15 -> 5.9642775 | E16: =E12+E14-E15 -> 6.4054197 | F16: =F12+F14-F15 -> 6.8321991
A17: (=) Sinergias después de impuestos | B17: =B16*(1-'Costo de capital'!$B$10) -> 0.1698125 | C17: =C16*(1-'Costo de capital'!$B$10) -> 2.4665875 | D17: =D16*(1-'Costo de capital'!$B$10) -> 3.8767804 | E17: =E16*(1-'Costo de capital'!$B$10) -> 4.1635228 | F17: =F16*(1-'Costo de capital'!$B$10) -> 4.4409294
A18: Flujo de caja libre de NutriFun (DCF) | B18: ='DCF NutriFun'!C23 -> 1.965 | C18: ='DCF NutriFun'!D23 -> 2.5045 | D18: ='DCF NutriFun'!E23 -> 4.613205 | E18: ='DCF NutriFun'!F23 -> 5.2197364 | F18: ='DCF NutriFun'!G23 -> 5.7123937
A19: (=) Flujo total para HealthySnacks | B19: =B17+B18 -> 2.1348125 | C19: =C17+C18 -> 4.9710875 | D19: =D17+D18 -> 8.4899854 | E19: =E17+E18 -> 9.3832592 | F19: =F17+F18 -> 10.153323
A20: Flujo acumulado (desde el pago del precio) | B20: =-$B$7+B19 -> -47.868873 | C20: =B20+C19 -> -42.897785 | D20: =C20+D19 -> -34.4078 | E20: =D20+E19 -> -25.024541 | F20: =E20+F19 -> -14.871218
A22: Valor presente de las sinergias (con valor terminal) | B22: =SUMPRODUCT(B17:F17,'DCF NutriFun'!C26:G26)+F17*(1+'DCF NutriFun'!B9)/('DCF NutriFun'!B8-'DCF NutriFun'!B9)*'DCF NutriFun'!G26 -> 43.482716
A23: Valor de NutriFun sin sinergias (DCF) | B23: ='DCF NutriFun'!B29 -> 56.603685
A24: (−) Contingencias detectadas en la due diligence | B24: ='Precio en 3 momentos'!C7+'Precio en 3 momentos'!C8 -> -4.6
A25: (−) Precio pagado | B25: =-B7 -> -50.003685
A26: (=) Valor presente neto para HealthySnacks | B26: =B22+B23+B24+B25 -> 45.482716
A28: Recuperación de la inversión (años, flujos sin descontar) | B28: =MATCH(TRUE(),INDEX(B37:I37>=0,0),0) -> 7
A29: Objetivo del caso | B29: 5
A30: ¿Se cumple el objetivo? | B30: =IF(B28<=B29,"Sí","No") -> No
A31: Recuperación con interpolación (años) | B31: =(B28-1)+(-INDEX(B37:I37,B28-1))/INDEX(B36:I36,B28) -> 6.4010969
A33: Calendario de recuperación de la inversión (millones de USD)
A34: Concepto | B34: Año 1 (2026) | C34: Año 2 (2027) | D34: Año 3 (2028) | E34: Año 4 (2029) | F34: Año 5 (2030) | G34: Año 6 (2031) | H34: Año 7 (2032) | I34: Año 8 (2033)
A35: Tipo de flujo | B35: Proyectado | C35: Proyectado | D35: Proyectado | E35: Proyectado | F35: Proyectado | G35: Perpetuidad | H35: Perpetuidad | I35: Perpetuidad
A36: (=) Flujo total para HealthySnacks | B36: =B19 -> 2.1348125 | C36: =C19 -> 4.9710875 | D36: =D19 -> 8.4899854 | E36: =E19 -> 9.3832592 | F36: =F19 -> 10.153323 | G36: =F36*(1+'DCF NutriFun'!$B$9) -> 10.508689 | H36: =G36*(1+'DCF NutriFun'!$B$9) -> 10.876494 | I36: =H36*(1+'DCF NutriFun'!$B$9) -> 11.257171
A37: Flujo acumulado (desde el pago del precio) | B37: =-$B$7+B36 -> -47.868873 | C37: =B37+C36 -> -42.897785 | D37: =C37+D36 -> -34.4078 | E37: =D37+E36 -> -25.024541 | F37: =E37+F36 -> -14.871218 | G37: =F37+G36 -> -4.3625282 | H37: =G37+H36 -> 6.5139654 | I37: =H37+I36 -> 17.771136
A38: ¿Inversión recuperada? | B38: =IF(B37>=0,"Sí","No") -> No | C38: =IF(C37>=0,"Sí","No") -> No | D38: =IF(D37>=0,"Sí","No") -> No | E38: =IF(E37>=0,"Sí","No") -> No | F38: =IF(F37>=0,"Sí","No") -> No | G38: =IF(G37>=0,"Sí","No") -> No | H38: =IF(H37>=0,"Sí","No") -> Sí | I38: =IF(I37>=0,"Sí","No") -> Sí
A40: Años 1 a 5: flujos proyectados (tabla superior). Años 6 a 8: el flujo de 2030 crece a la tasa de perpetuidad (3.5%), igual que en el valor terminal.
A41: La inversión se recupera en el año en que el flujo acumulado deja de ser negativo.

Sheet Objetivos
A1: Objetivos financieros y operativos del caso: ¿son alcanzables? (millones de USD)
A3: Supuesto | B3: Valor | C3: Comentario
A4: Crecimiento anual del EBITDA de HealthySnacks | B4: 0.04 | C4: Supuesto: mercado en crecimiento
A5: Crecimiento anual de ventas de HealthySnacks | B5: 0.05 | C5: Supuesto
A7: Objetivo | B7: Meta | C7: Proyección | D7: ¿Se cumple? | E7: Cálculo
A8: EBITDA combinado al tercer año (2028) | B8: 40 | C8: ='Datos del caso'!B5*(1+B4)^3+'DCF NutriFun'!E14+'Sinergias y VPN'!D16 -> 44.637078 | D8: =IF(C8>=B8,"Sí","No") -> Sí | E8: EBITDA HS × (1+4%)^3 + EBITDA NutriFun 2028 + sinergias 2028
A9: Incremento de ventas conjuntas el primer año | B9: 0.2 | C9: =('Datos del caso'!B4*(1+B5)+'DCF NutriFun'!C13+'Sinergias y VPN'!B13)/'Datos del caso'!D4-1 -> 0.093939394 | D9: =IF(C9>=B9,"Sí","No") -> No | E9: (Ventas HS 2026 + NutriFun 2026 + ventas cruzadas) / 165 − 1
A10: Recuperación de la inversión (años) | B10: 5 | C10: ='Sinergias y VPN'!B28 -> 7 | D10: =IF(C10<=B10,"Sí","No") -> No | E10: Hoja Sinergias y VPN
A11: Reducción de costos de producción de NutriFun (año completo) | B11: 0.1 | C11: ='Sinergias y VPN'!D12/('DCF NutriFun'!E13*'Sinergias y VPN'!B4) -> 0.1 | D11: =IF(C11>=B11,"Sí","No") -> Sí | E11: Ahorro 2028 / costo de producción 2028
A13: El ROE de 15% al tercer año no se proyecta porque el caso no informa el capital contable de HealthySnacks; se mide como KPI.

Sheet KPI
A1: Tablero de indicadores clave (KPI) de la integración
A3: Tipo | B3: Indicador | C3: Fórmula o criterio de medición | D3: Meta | E3: Frecuencia
A4: Financiero | B4: ROE | C4: Utilidad neta / capital contable promedio | D4: 15% al tercer año | E4: Trimestral
A5: Financiero | B5: ROA | C5: Utilidad neta / activo total promedio | D5: ≥ 8% al tercer año | E5: Trimestral
A6: Financiero | B6: EBITDA combinado | C6: Utilidad de operación + depreciación y amortización | D6: USD 40 M en 2028 | E6: Mensual
A7: Financiero | B7: Margen EBITDA | C7: EBITDA / ventas netas | D7: ≥ 20% en 2028 | E7: Mensual
A8: Financiero | B8: Deuda neta / EBITDA | C8: (Deuda − efectivo) / EBITDA de 12 meses | D8: ≤ 2.0 veces | E8: Trimestral
A9: Financiero | B9: Recuperación de la inversión | C9: Flujo acumulado desde el pago / precio pagado | D9: 100% en 7 años (objetivo del caso: 5) | E9: Anual
A10: Operativo | B10: Incremento en ventas conjuntas | C10: (Ventas del periodo / ventas del mismo periodo anterior) − 1 | D10: +10% el primer año; +20% acumulado al segundo | E10: Mensual
A11: Operativo | B11: Cumplimiento del presupuesto maestro | C11: Resultado real / presupuestado por rubro | D11: 95% a 105% | E11: Mensual
A12: Operativo | B12: Rotación de inventarios | C12: Costo de ventas / inventario promedio | D12: ≥ 12 veces al año | E12: Mensual
A13: Operativo | B13: Ahorro en costos de producción | C13: (Costo unitario anterior − actual) / costo unitario anterior | D13: 10% al segundo año | E13: Trimestral
A14: Operativo | B14: Satisfacción de clientes | C14: Promedio de encuesta (escala 1 a 10) a cadenas y distribuidores | D14: ≥ 8.5 | E14: Semestral
A15: Operativo | B15: Rotación de personal clave | C15: Bajas de personal clave / total de personal clave | D15: ≤ 10% anual | E15: Trimestral
A17: Indicadores tomados del caso y de la lista del Tema 6; metas propuestas por el autor.

Sheet Registro NIF B-7
A1: Reconocimiento inicial de la adquisición según la NIF B-7 (ilustrativo, millones de USD)
A3: Concepto | B3: Valor | C3: Comentario
A4: Contraprestación pagada por el 100% de las acciones | B4: ='Precio en 3 momentos'!D14 -> 40.003685 | C4: Precio final menos deuda liquidada
A5: Activos identificables a valor razonable (planta, inventarios, cuentas por cobrar) | B5: 30 | C5: Supuesto
A6: Marca NutriFun (activo intangible identificable) | B6: 8 | C6: Supuesto: valuación por regalías
A7: (−) Pasivos asumidos a valor razonable (sin la deuda liquidada) | B7: -12 | C7: Supuesto: proveedores, laborales y fiscales
A8: (=) Activos netos identificables a valor razonable | B8: =B5+B6+B7 -> 26
A9: Crédito mercantil = contraprestación − activos netos | B9: =B4-B8 -> 14.003685 | C9: Se reconoce como activo y se somete a pruebas de deterioro
A11: Cifras en azul = supuestos ilustrativos; el caso no informa el balance de NutriFun.

Sheet Presupuesto maestro 2026
A1: Presupuesto maestro conjunto 2026 (primer año posterior a la compra, millones de USD)
A3: Supuesto | B3: Valor | C3: Comentario
A4: Costo de ventas / ventas (ambas empresas) | B4: 0.55 | C4: Supuesto
A6: Concepto | B6: HealthySnacks | C6: NutriFun | D6: Ventas cruzadas | E6: Integración | F6: Total
A7: Ventas netas | B7: ='Datos del caso'!B4*(1+Objetivos!B5) -> 126 | C7: ='DCF NutriFun'!C13 -> 49.5 | D7: ='Sinergias y VPN'!B13 -> 5 | E7: 0 | F7: =SUM(B7:E7) -> 180.5
A8: (−) Costo de ventas | B8: =B7*$B$4 -> 69.3 | C8: =C7*$B$4-'Sinergias y VPN'!B12 -> 25.86375 | D8: =D7*$B$4 -> 2.75 | E8: 0 | F8: =SUM(B8:E8) -> 97.91375
A9: (=) Utilidad bruta | B9: =B7-B8 -> 56.7 | C9: =C7-C8 -> 23.63625 | D9: =D7-D8 -> 2.25 | E9: =E7-E8 -> 0 | F9: =F7-F8 -> 82.58625
A10: (−) Gastos de operación (sin depreciación) | B10: =B9-'Datos del caso'!B5*(1+Objetivos!B4) -> 30.7 | C10: =C9-'DCF NutriFun'!C14-'Sinergias y VPN'!B12 -> 13.475 | D10: =D9-D7*'Sinergias y VPN'!B6 -> 1.35 | E10: ='Sinergias y VPN'!B15 -> 2 | F10: =SUM(B10:E10) -> 47.525
A11: (=) EBITDA | B11: =B9-B10 -> 26 | C11: =C9-C10 -> 10.16125 | D11: =D9-D10 -> 0.9 | E11: =E9-E10 -> -2 | F11: =F9-F10 -> 35.06125
A12: Margen EBITDA | B12: =IF(B7=0,"",B11/B7) -> 0.20634921 | C12: =IF(C7=0,"",C11/C7) -> 0.20527778 | D12: =IF(D7=0,"",D11/D7) -> 0.18 | F12: =IF(F7=0,"",F11/F7) -> 0.19424515
A14: El ahorro en compras se refleja en el costo de ventas de NutriFun; los costos de integración, en gastos de operación.

Sheet Sensibilidad
A1: Sensibilidad del valor presente neto a la captura de sinergias (millones de USD)
A3: Sinergias capturadas | B3: VP de sinergias | C3: VPN para HealthySnacks | D3: Lectura
A4: 0 | B4: ='Sinergias y VPN'!B22*A4 -> 0 | C4: ='Sinergias y VPN'!B23+'Sinergias y VPN'!B24+'Sinergias y VPN'!B25+B4 -> 2 | D4: El precio solo se cubre con el valor propio de NutriFun
A5: 0.5 | B5: ='Sinergias y VPN'!B22*A5 -> 21.741358 | C5: ='Sinergias y VPN'!B23+'Sinergias y VPN'!B24+'Sinergias y VPN'!B25+B5 -> 23.741358 | D5: Aun con la mitad de las sinergias se crea valor
A6: 1 | B6: ='Sinergias y VPN'!B22*A6 -> 43.482716 | C6: ='Sinergias y VPN'!B23+'Sinergias y VPN'!B24+'Sinergias y VPN'!B25+B6 -> 45.482716 | D6: Escenario base

Sheet Sensibilidad CapEx
A1: Sensibilidad de la recuperación de la inversión al CapEx de NutriFun (millones de USD)
A3: Escenario de CapEx | B3: 2026 | C3: 2027 | D3: 2028 | E3: 2029 | F3: 2030 | G3: Total 5 años | H3: Factor
A4: Base del modelo (incluye planta de Bogotá) | B4: ='DCF NutriFun'!C20 -> 3.5 | C4: ='DCF NutriFun'!D20 -> 3.5 | D4: ='DCF NutriFun'!E20 -> 2 | E4: ='DCF NutriFun'!F20 -> 2 | F4: ='DCF NutriFun'!G20 -> 2.1 | G4: =SUM(B4:F4) -> 13.1
A5: CapEx reducido | B5: =B$4*$H$5 -> 1.75 | C5: =C$4*$H$5 -> 1.75 | D5: =D$4*$H$5 -> 1 | E5: =E$4*$H$5 -> 1 | F5: =F$4*$H$5 -> 1.05 | G5: =SUM(B5:F5) -> 6.55 | H5: 0.5
A6: CapEx igual a la depreciación (mantenimiento) | B6: ='DCF NutriFun'!C15 -> 1.2 | C6: ='DCF NutriFun'!D15 -> 1.3 | D6: ='DCF NutriFun'!E15 -> 1.4 | E6: ='DCF NutriFun'!F15 -> 1.5 | F6: ='DCF NutriFun'!G15 -> 1.6 | G6: =SUM(B6:F6) -> 7
A7: Sin CapEx (caso extremo) | B7: 0 | C7: 0 | D7: 0 | E7: 0 | F7: 0 | G7: =SUM(B7:F7) -> 0
A10: Flujo total para HealthySnacks por escenario (después de sinergias)
A11: Escenario | B11: Año 1 | C11: Año 2 | D11: Año 3 | E11: Año 4 | F11: Año 5 | G11: Año 6 | H11: Año 7 | I11: Año 8 | J11: Año 9 | K11: Año 10
A12: Base del modelo (incluye planta de Bogotá) | B12: ='Sinergias y VPN'!B19+B$4-B4 -> 2.1348125 | C12: ='Sinergias y VPN'!C19+C$4-C4 -> 4.9710875 | D12: ='Sinergias y VPN'!D19+D$4-D4 -> 8.4899854 | E12: ='Sinergias y VPN'!E19+E$4-E4 -> 9.3832592 | F12: ='Sinergias y VPN'!F19+F$4-F4 -> 10.153323 | G12: =F12*(1+'DCF NutriFun'!$B$9) -> 10.508689 | H12: =G12*(1+'DCF NutriFun'!$B$9) -> 10.876494 | I12: =H12*(1+'DCF NutriFun'!$B$9) -> 11.257171 | J12: =I12*(1+'DCF NutriFun'!$B$9) -> 11.651172 | K12: =J12*(1+'DCF NutriFun'!$B$9) -> 12.058963
A13: CapEx reducido | B13: ='Sinergias y VPN'!B19+B$4-B5 -> 3.8848125 | C13: ='Sinergias y VPN'!C19+C$4-C5 -> 6.7210875 | D13: ='Sinergias y VPN'!D19+D$4-D5 -> 9.4899854 | E13: ='Sinergias y VPN'!E19+E$4-E5 -> 10.383259 | F13: ='Sinergias y VPN'!F19+F$4-F5 -> 11.203323 | G13: =F13*(1+'DCF NutriFun'!$B$9) -> 11.595439 | H13: =G13*(1+'DCF NutriFun'!$B$9) -> 12.00128 | I13: =H13*(1+'DCF NutriFun'!$B$9) -> 12.421325 | J13: =I13*(1+'DCF NutriFun'!$B$9) -> 12.856071 | K13: =J13*(1+'DCF NutriFun'!$B$9) -> 13.306033
A14: CapEx igual a la depreciación (mantenimiento) | B14: ='Sinergias y VPN'!B19+B$4-B6 -> 4.4348125 | C14: ='Sinergias y VPN'!C19+C$4-C6 -> 7.1710875 | D14: ='Sinergias y VPN'!D19+D$4-D6 -> 9.0899854 | E14: ='Sinergias y VPN'!E19+E$4-E6 -> 9.8832592 | F14: ='Sinergias y VPN'!F19+F$4-F6 -> 10.653323 | G14: =F14*(1+'DCF NutriFun'!$B$9) -> 11.026189 | H14: =G14*(1+'DCF NutriFun'!$B$9) -> 11.412106 | I14: =H14*(1+'DCF NutriFun'!$B$9) -> 11.81153 | J14: =I14*(1+'DCF NutriFun'!$B$9) -> 12.224933 | K14: =J14*(1+'DCF NutriFun'!$B$9) -> 12.652806
A15: Sin CapEx (caso extremo) | B15: ='Sinergias y VPN'!B19+B$4-B7 -> 5.6348125 | C15: ='Sinergias y VPN'!C19+C$4-C7 -> 8.4710875 | D15: ='Sinergias y VPN'!D19+D$4-D7 -> 10.489985 | E15: ='Sinergias y VPN'!E19+E$4-E7 -> 11.383259 | F15: ='Sinergias y VPN'!F19+F$4-F7 -> 12.253323 | G15: =F15*(1+'DCF NutriFun'!$B$9) -> 12.682189 | H15: =G15*(1+'DCF NutriFun'!$B$9) -> 13.126066 | I15: =H15*(1+'DCF NutriFun'!$B$9) -> 13.585478 | J15: =I15*(1+'DCF NutriFun'!$B$9) -> 14.06097 | K15: =J15*(1+'DCF NutriFun'!$B$9) -> 14.553104
A17: Flujo acumulado desde el pago del precio
A18: Escenario | B18: Año 1 | C18: Año 2 | D18: Año 3 | E18: Año 4 | F18: Año 5 | G18: Año 6 | H18: Año 7 | I18: Año 8 | J18: Año 9 | K18: Año 10
A19: Base del modelo (incluye planta de Bogotá) | B19: =-'Sinergias y VPN'!$B$7+B12 -> -47.868873 | C19: =B19+C12 -> -42.897785 | D19: =C19+D12 -> -34.4078 | E19: =D19+E12 -> -25.024541 | F19: =E19+F12 -> -14.871218 | G19: =F19+G12 -> -4.3625282 | H19: =G19+H12 -> 6.5139654 | I19: =H19+I12 -> 17.771136 | J19: =I19+J12 -> 29.422308 | K19: =J19+K12 -> 41.481271
A20: CapEx reducido | B20: =-'Sinergias y VPN'!$B$7+B13 -> -46.118873 | C20: =B20+C13 -> -39.397785 | D20: =C20+D13 -> -29.9078 | E20: =D20+E13 -> -19.524541 | F20: =E20+F13 -> -8.3212176 | G20: =F20+G13 -> 3.2742218 | H20: =G20+H13 -> 15.275502 | I20: =H20+I13 -> 27.696826 | J20: =I20+J13 -> 40.552897 | K20: =J20+K13 -> 53.858931
A21: CapEx igual a la depreciación (mantenimiento) | B21: =-'Sinergias y VPN'!$B$7+B14 -> -45.568873 | C21: =B21+C14 -> -38.397785 | D21: =C21+D14 -> -29.3078 | E21: =D21+E14 -> -19.424541 | F21: =E21+F14 -> -8.7712176 | G21: =F21+G14 -> 2.2549718 | H21: =G21+H14 -> 13.667078 | I21: =H21+I14 -> 25.478608 | J21: =I21+J14 -> 37.703541 | K21: =J21+K14 -> 50.356347
A22: Sin CapEx (caso extremo) | B22: =-'Sinergias y VPN'!$B$7+B15 -> -44.368873 | C22: =B22+C15 -> -35.897785 | D22: =C22+D15 -> -25.4078 | E22: =D22+E15 -> -14.024541 | F22: =E22+F15 -> -1.7712176 | G22: =F22+G15 -> 10.910972 | H22: =G22+H15 -> 24.037038 | I22: =H22+I15 -> 37.622516 | J22: =I22+J15 -> 51.683486 | K22: =J22+K15 -> 66.23659
A24: Resumen: ¿se alcanza la meta de recuperación en 5 años?
A25: Escenario | B25: CapEx 5 años | C25: Ahorro vs. base | D25: Acumulado al año 5 | E25: Recuperación (años) | F25: Meta | G25: ¿Cumple?
A26: Base del modelo (incluye planta de Bogotá) | B26: =G4 -> 13.1 | C26: =$G$4-G4 -> 0 | D26: =F19 -> -14.871218 | E26: =(MATCH(TRUE(),INDEX(B19:K19>=0,0),0)-1)+(-INDEX(B19:K19,MATCH(TRUE(),INDEX(B19:K19>=0,0),0)-1))/INDEX(B12:K12,MATCH(TRUE(),INDEX(B19:K19>=0,0),0)) -> 6.4010969 | F26: ='Sinergias y VPN'!$B$29 -> 5 | G26: =IF(E26<=F26,"Sí","No") -> No
A27: CapEx reducido | B27: =G5 -> 6.55 | C27: =$G$4-G5 -> 6.55 | D27: =F20 -> -8.3212176 | E27: =(MATCH(TRUE(),INDEX(B20:K20>=0,0),0)-1)+(-INDEX(B20:K20,MATCH(TRUE(),INDEX(B20:K20>=0,0),0)-1))/INDEX(B13:K13,MATCH(TRUE(),INDEX(B20:K20>=0,0),0)) -> 5.7176285 | F27: ='Sinergias y VPN'!$B$29 -> 5 | G27: =IF(E27<=F27,"Sí","No") -> No
A28: CapEx igual a la depreciación (mantenimiento) | B28: =G6 -> 7 | C28: =$G$4-G6 -> 6.1 | D28: =F21 -> -8.7712176 | E28: =(MATCH(TRUE(),INDEX(B21:K21>=0,0),0)-1)+(-INDEX(B21:K21,MATCH(TRUE(),INDEX(B21:K21>=0,0),0)-1))/INDEX(B14:K14,MATCH(TRUE(),INDEX(B21:K21>=0,0),0)) -> 5.7954895 | F28: ='Sinergias y VPN'!$B$29 -> 5 | G28: =IF(E28<=F28,"Sí","No") -> No
A29: Sin CapEx (caso extremo) | B29: =G7 -> 0 | C29: =$G$4-G7 -> 13.1 | D29: =F22 -> -1.7712176 | E29: =(MATCH(TRUE(),INDEX(B22:K22>=0,0),0)-1)+(-INDEX(B22:K22,MATCH(TRUE(),INDEX(B22:K22>=0,0),0)-1))/INDEX(B15:K15,MATCH(TRUE(),INDEX(B22:K22>=0,0),0)) -> 5.1396618 | F29: ='Sinergias y VPN'!$B$29 -> 5 | G29: =IF(E29<=F29,"Sí","No") -> No
A31: Recuperación interpolada con flujos sin descontar. Años 6 a 10: el flujo del año 5 crece a la tasa de perpetuidad.
A32: El modelo mantiene las ventas sin cambio en todos los escenarios; en la práctica, recortar el CapEx de la planta de Bogotá reduciría el crecimiento de NutriFun,
A33: por lo que estos resultados son el mejor caso posible. Ni con CapEx en cero el acumulado del año 5 llega a cero: el CapEx total (13.1) es menor que el faltante (14.9).
